{"data":{"markdownRemark":{"html":"<p>I have generalized anxiety.</p>\n<p>Essentially, I feel anxiety while doing daily activities.</p>\n<p>I actually didn't realize how extreme it was until a couple years ago when I really wanted to describe what I was thinking to a friend. Let them in on my hell. I wrote down every thought I had. It was pages of thoughts for doing an activity. That activity was riding the bus for about 10 minutes from my apartment to downtown Austin. </p>\n<p>Like most other episodes of anxiety, I turned to the phrase that has always pushed me past my anxiety.</p>\n<blockquote>\n<p>\"Fuck it.\"</p>\n</blockquote>\n<p>And then, I just do whatever I was having anxiety about.</p>","frontmatter":{"title":"F*ck It","date":"June 28, 2019","tags":["personal","mental-health"]}}},"pageContext":{"slug":"blog/2019/06-25-2019-f*ck-it/","date":"2019-06-28T21:50:00.000Z"}}